adolf/__init__.py
adolf/ar.py
adolf/blgr.py
adolf/code.py
adolf/corpus.py
adolf/dt.py
adolf/gd.py
adolf/grams.py
adolf/km.py
adolf/knn.py
adolf/mlgr.py
adolf/mlr.py
adolf/nb.py
adolf/pos.py
adolf/slr.py
adolf/smoothing.py
adolf/stemming.py
adolf/stopwords.py
adolf/tokenizer.py
adolf/wordcount.py
adolf-0.4.0.dist-info/METADATA
adolf-0.4.0.dist-info/WHEEL
adolf-0.4.0.dist-info/top_level.txt
adolf-0.4.0.dist-info/RECORD
