Metadata-Version: 2.4
Name: adolf
Version: 0.4.0
Summary: A sample Python package
Author-email: Capy Bara <capyslayers@gmail.com>
Requires-Dist: IPython
